[
  {
    "category": "Животные",
    "word": "ЖИРАФ",
    "hint": "Самое высокое животное на земле"
  },
  {
    "category": "Животные",
    "word": "КРОКОДИЛ",
    "hint": "Живёт в реках и болотах, очень древний"
  },
  {
    "category": "Животные",
    "word": "ДЕЛЬФИН",
    "hint": "Умное морское млекопитающее"
  },
  {
    "category": "Животные",
    "word": "СЛОН",
    "hint": "Самое крупное наземное животное"
  },
  {
    "category": "Животные",
    "word": "ПИНГВИН",
    "hint": "Птица, которая не умеет летать"
  },
  {
    "category": "Города",
    "word": "МОСКВА",
    "hint": "Столица России"
  },
  {
    "category": "Города",
    "word": "ПАРИЖ",
    "hint": "Город с Эйфелевой башней"
  },
  {
    "category": "Города",
    "word": "ТОКИО",
    "hint": "Столица Японии"
  },
  {
    "category": "Города",
    "word": "ЛОНДОН",
    "hint": "Столица Великобритании"
  },
  {
    "category": "Города",
    "word": "РИМ",
    "hint": "Вечный город"
  },
  {
    "category": "Фрукты",
    "word": "АНАНАС",
    "hint": "Тропический фрукт в колючей шкурке"
  },
  {
    "category": "Фрукты",
    "word": "МАНГО",
    "hint": "Сладкий жёлтый тропический фрукт"
  },
  {
    "category": "Фрукты",
    "word": "АРБУЗ",
    "hint": "Большая зелёная ягода с красной мякотью"
  },
  {
    "category": "Фрукты",
    "word": "АБРИКОС",
    "hint": "Маленький оранжевый фрукт с косточкой"
  },
  {
    "category": "Фрукты",
    "word": "КЛУБНИКА",
    "hint": "Красная ягода, растёт на грядке"
  },
  {
    "category": "Профессии",
    "word": "АРХИТЕКТОР",
    "hint": "Проектирует здания и сооружения"
  },
  {
    "category": "Профессии",
    "word": "ПРОГРАММИСТ",
    "hint": "Пишет код и создаёт программы"
  },
  {
    "category": "Профессии",
    "word": "ХИРУРГ",
    "hint": "Врач, который делает операции"
  },
  {
    "category": "Профессии",
    "word": "ПИЛОТ",
    "hint": "Управляет самолётом"
  },
  {
    "category": "Профессии",
    "word": "АСТРОНАВТ",
    "hint": "Летает в космос"
  },
  {
    "category": "Спорт",
    "word": "ФУТБОЛ",
    "hint": "Игра с мячом и воротами"
  },
  {
    "category": "Спорт",
    "word": "ТЕННИС",
    "hint": "Игра с ракеткой и мячиком"
  },
  {
    "category": "Спорт",
    "word": "ПЛАВАНИЕ",
    "hint": "Спорт в воде"
  },
  {
    "category": "Спорт",
    "word": "ГИМНАСТИКА",
    "hint": "Акробатика и упражнения на снарядах"
  },
  {
    "category": "Спорт",
    "word": "БАСКЕТБОЛ",
    "hint": "Мяч в кольцо с сеткой"
  }
]